jupyter_spark/__init__.py
jupyter_spark/handlers.py
jupyter_spark/spark.py
jupyter_spark/static/extension.js
jupyter_spark-0.4.0.dist-info/DESCRIPTION.rst
jupyter_spark-0.4.0.dist-info/METADATA
jupyter_spark-0.4.0.dist-info/RECORD
jupyter_spark-0.4.0.dist-info/WHEEL
jupyter_spark-0.4.0.dist-info/metadata.json
jupyter_spark-0.4.0.dist-info/top_level.txt
