Metadata-Version: 2.0
Name: jupyter-spark
Version: 0.4.0
Summary: Jupyter Notebook extension for Apache Spark integration
Home-page: https://github.com/mozilla/jupyter-spark
Author: Mozilla Firefox Data Platform
Author-email: fx-data-platform@mozilla.com
License: MPL2
Platform: UNKNOWN
Requires-Dist: ipython (>=4)
Requires-Dist: jupyter
Requires-Dist: notebook (>=4.2)
Requires-Dist: beautifulsoup4
Requires-Dist: widgetsnbextension
